README.md
setup.py
removeaccents/__init__.py
removeaccents/removeaccents.py
removeaccents.egg-info/PKG-INFO
removeaccents.egg-info/SOURCES.txt
removeaccents.egg-info/dependency_links.txt
removeaccents.egg-info/top_level.txt